subfind/__init__.py
subfind/cmd.py
subfind/event.py
subfind/finder.py
subfind/movie_parser.py
subfind/processor.py
subfind/provider.py
subfind/tokenizer.py
subfind/exception/__init__.py
subfind/model/__init__.py
subfind/movie/__init__.py
subfind/movie/alice.py
subfind/release/__init__.py
subfind/release/alice.py
subfind/scenario/__init__.py
subfind/subtitle/__init__.py
subfind/subtitle/alice.py
subfind/utils/__init__.py
subfind/utils/process.py
subfind/utils/subtitle.py
subfind-4.7.1.dist-info/DESCRIPTION.rst
subfind-4.7.1.dist-info/METADATA
subfind-4.7.1.dist-info/RECORD
subfind-4.7.1.dist-info/WHEEL
subfind-4.7.1.dist-info/entry_points.txt
subfind-4.7.1.dist-info/metadata.json
subfind-4.7.1.dist-info/top_level.txt
subfind_cli/__init__.py
subfind_cli/cli.py
subfind_cli/utils.py
subfind_provider_opensubtitles/__init__.py
subfind_provider_opensubtitles/utils.py
subfind_provider_subscene/__init__.py
subfind_provider_subscene/language.py
subfind_web/__init__.py
subfind_web/api.py
subfind_web/app.py
subfind_web/bootstrap.py
subfind_web/crossdomain.py
subfind_web/script.py
subfind_web/utils.py
subfind_web/validate.py
subfind_web/conf/api.yml
subfind_web/conf/services.yml
subfind_web/exception/__init__.py
subfind_web/exception/api.py
subfind_web/model/__init__.py
subfind_web/model/config.py
subfind_web/service/ConfigService.py
subfind_web/service/ReleaseService.py
subfind_web/service/__init__.py
subfind_web/ui/build/asset-manifest.json
subfind_web/ui/build/favicon.ico
subfind_web/ui/build/index.html
subfind_web/ui/build/service-worker.js
subfind_web/ui/build/static/css/main.6dcbde58.css
subfind_web/ui/build/static/css/main.6dcbde58.css.map
subfind_web/ui/build/static/js/main.16b0ef59.js
subfind_web/ui/build/static/js/main.16b0ef59.js.map
