Metadata-Version: 2.0
Name: subfind
Version: 4.7.1
Summary: Subtitle crawler written in Python
Home-page: https://github.com/thongdong7/subfind
Author: Thong Dong
Author-email: thongdong7@gmail.com
License: UNKNOWN
Platform: UNKNOWN
Classifier: Development Status :: 5 - Production/Stable
Classifier: Environment :: Console
Classifier: License :: OSI Approved :: Python Software Foundation License
Classifier: Programming Language :: Python
Classifier: Programming Language :: Python :: 2.6
Classifier: Programming Language :: Python :: 2.7
Classifier: Programming Language :: Python :: 3.3
Classifier: Programming Language :: Python :: 3.4
Classifier: Programming Language :: Python :: 3.5
Requires-Dist: six (==1.10.0)
Provides-Extra: cli
Requires-Dist: click (==6.6); extra == 'cli'
Requires-Dist: pyyaml (==3.11); extra == 'cli'
Requires-Dist: requests (==2.9.1); extra == 'cli'
Requires-Dist: babelfish (==0.5.5); extra == 'cli'
Requires-Dist: beautifulsoup4 (==4.4.1); extra == 'cli'
Provides-Extra: opensubtitles
Requires-Dist: requests (==2.9.1); extra == 'opensubtitles'
Requires-Dist: babelfish (==0.5.5); extra == 'opensubtitles'
Provides-Extra: subscene
Requires-Dist: requests (==2.9.1); extra == 'subscene'
Requires-Dist: beautifulsoup4 (==4.4.1); extra == 'subscene'
Provides-Extra: web
Requires-Dist: flask (==0.10.1); extra == 'web'
Requires-Dist: tornado (==4.3); extra == 'web'
Requires-Dist: click (==6.6); extra == 'web'
Requires-Dist: gevent (==1.2.2); extra == 'web'
